caplib/__init__.py
caplib/analytics.py
caplib/cmanalytics.py
caplib/cmmarket.py
caplib/cr_entity.py
caplib/cranalytics.py
caplib/crmarket.py
caplib/datetime.py
caplib/eq_entity.py
caplib/eqanalytics.py
caplib/fi_entity.py
caplib/fianalytics.py
caplib/fimarket.py
caplib/fx_entity.py
caplib/fxanalytics.py
caplib/fxmarket.py
caplib/ir_entity.py
caplib/iranalytics.py
caplib/irmarket.py
caplib/market.py
caplib/mktrisk.py
caplib/numerics.py
caplib/processrequest.py
caplib/staticdata.py
caplib/utility.py
caplib-1.0.3.dist-info/METADATA
caplib-1.0.3.dist-info/WHEEL
caplib-1.0.3.dist-info/top_level.txt
caplib-1.0.3.dist-info/RECORD
