Metadata-Version: 2.4
Name: caplib
Version: 1.0.3
Home-page: 
Author: caprisktech.com
Requires-Python: >= 3.8.0
Requires-Dist: pandas>=2.0.3
Requires-Dist: caplibproto==0.0.7
Dynamic: author
Dynamic: requires-dist
Dynamic: requires-python
